{
 "accountAssociation": {
    "header": "eyJmaWQiOjMyNDg2MywidHlwZSI6ImN1c3RvZHkiLCJrZXkiOiIweDBBNDE5MjJDMjhiODY2YjM4ZjFlOEQ4NjA2RDljMDk4MTM2NThjNzIifQ",
    "payload": "eyJkb21haW4iOiJmY21hcHAubmV0bGlmeS5hcHAifQ",
    "signature": "MHg5YTZmN2ZkMjU3OWE3MTlhNmRlMTliMzljOGVlODhjM2M4MDFkMTgzZThmNjQ1MWQ2ZDM2ZDVjYmQxMTI3ZjA3Njc3NGE3YTQyMDYyZTAxYTIwMmFlYTE4ZDhlMDg1OWEwYzliNThkMjgzMTI5NDI0YjhmM2FmMmM2MWYxY2ZlZDFi"
  },
  "frame": {
    "version": "1",
    "name": "StremeINU Superfluid River",
    "iconUrl": "https://fcmapp.netlify.app/icon.svg",
    "homeUrl": "https://fcmapp.netlify.app",
    "imageUrl": "https://fcmapp.netlify.app/og-image.svg",
    "buttonTitle": "🚀 Launch App",
    "splashImageUrl": "https://fcmapp.netlify.app/splash.svg",
    "splashBackgroundColor": "#000000",
    "subtitle": "Streme'n the Trendiest Tokens ",
    "description": "A fun game to catch the trendiest tokens on Streme.Fun in the Superfluid River.",
    "primaryCategory": "social",
    "tags": [
      "farcaster",
      "mini-app",
      "streme",
      "react",
      "typescript"
    ],
    "heroImageUrl": "https://fcmapp.netlify.app/og-image.svg",
    "tagline": "Streme'n the Trendiest Tokens",
    "ogTitle": "StremeINU Superfluid River",
    "ogDescription": "A fun game to catch the trendiest tokens on Streme.Fun in the Superfluid River.",
    "ogImageUrl": "https://fcmapp.netlify.app/og-image.svg"
  }
}